lumos/__init__.py
lumos/models/__init__.py
lumos/models/base.py
lumos/models/composition.py
lumos/models/drone_model.py
lumos/models/kinematics.py
lumos/models/ml.py
lumos/models/simple_vehicle_on_track.py
lumos/models/test_utils.py
lumos/models/tracks.py
lumos/models/tree_utils.py
lumos/models/aero/__init__.py
lumos/models/aero/aero.py
lumos/models/tires/__init__.py
lumos/models/tires/base.py
lumos/models/tires/pacejka.py
lumos/models/tires/perantoni.py
lumos/models/tires/utils.py
lumos/models/vehicles/__init__.py
lumos/models/vehicles/simple_vehicle.py
lumos/numpy/__init__.py
lumos/numpy/utils.py
lumos/numpy/casadi_numpy/__init__.py
lumos/numpy/casadi_numpy/arithmetic.py
lumos/numpy/casadi_numpy/array.py
lumos/numpy/casadi_numpy/calculus.py
lumos/numpy/casadi_numpy/conditionals.py
lumos/numpy/casadi_numpy/determine_type.py
lumos/numpy/casadi_numpy/finite_difference_operators.py
lumos/numpy/casadi_numpy/integrate.py
lumos/numpy/casadi_numpy/interpolate.py
lumos/numpy/casadi_numpy/linalg.py
lumos/numpy/casadi_numpy/linalg_top_level.py
lumos/numpy/casadi_numpy/logicals.py
lumos/numpy/casadi_numpy/rotations.py
lumos/numpy/casadi_numpy/spacing.py
lumos/numpy/casadi_numpy/trig.py
lumos/optimal_control/__init__.py
lumos/optimal_control/collocation.py
lumos/optimal_control/config.py
lumos/optimal_control/convolution.py
lumos/optimal_control/fixed_mesh_ocp.py
lumos/optimal_control/model_solver.py
lumos/optimal_control/nlp.py
lumos/optimal_control/scaled_mesh_ocp.py
lumos/optimal_control/transcription.py
lumos/optimal_control/utils.py
lumos/simulations/__init__.py
lumos/simulations/drone_simulation.py
lumos/simulations/laptime_simulation.py
numagic_lumos-0.0.2rc7.dist-info/LICENSE
numagic_lumos-0.0.2rc7.dist-info/METADATA
numagic_lumos-0.0.2rc7.dist-info/WHEEL
numagic_lumos-0.0.2rc7.dist-info/top_level.txt
numagic_lumos-0.0.2rc7.dist-info/RECORD
