Metadata-Version: 2.1
Name: numagic-lumos
Version: 0.0.2rc7
Summary: lumos - scalable accelerated optimal control
Home-page: https://github.com/numagic/lumos
Author: Yunlong Xu
Author-email: yunlong@numagic.io
Project-URL: Bug Tracker, https://github.com/numagic/lumos/issues
Classifier: Programming Language :: Python :: 3
Classifier: Operating System :: OS Independent
Requires-Python: >=3.7
License-File: LICENSE
